{
    "ProductSections": [{
        "attributes": {
            "ovf:required": "false"
        },
        "Info": "Appliance ISV branding information",
        "Product": "VMware Sample Appliance",
        "Vendor": "VMware Inc.",
        "Version": "9.0",
        "FullVersion": "9.0 build XXX",
        "ProductUrl": "",
        "VendorUrl": "http://www.vmware.com",

        "categories": [{
            "name": "Application",
            "attributes": {
                "ovf:msgid": "app.category"
            },
            "properties": [
                {
                    "attributes": {
                        "ovf:key": "enable_sshd",
                        "ovf:value": "False",
                        "ovf:type": "boolean",
                        "ovf:userConfigurable": "true"
                    },
                    "Label": {
                        "ovf:msgid": "enable_sshd.label",
                        "value" : "Enable SSHD"
                    },
                    "Description": {
                        "ovf:msgid": "enable_sshd.description",
                        "value" : "Determines whether the SSHD service will be enabled and started by default in the appliance."
                    }
                },
                {
                    "attributes": {
                        "ovf:key": "varoot-password",
                        "ovf:type": "string",
                        "ovf:userConfigurable": "true",
                        "ovf:password": "true",
                        "ovf:qualifiers": "MinLen(8),MaxLen(32)"
                    },
                    "Label": {
                        "value" : "Initial root password"
                    },
                    "Description": {
                        "value" : "This will be used as an initial password for the root user account."
                    }
                },
                {
                    "attributes": {
                        "ovf:key": "vaadmin-password",
                        "ovf:type": "string",
                        "ovf:userConfigurable": "true",
                        "ovf:password": "true",
                        "ovf:qualifiers": "MinLen(8),MaxLen(32)"
                    },
                    "Label": {
                        "value" : "Initial admin user password"
                    },
                    "Description": {
                        "value" : "This will be used as an initial password for the admin user account."
                    }
                },
                {
                    "attributes": {
                        "ovf:key": "ntpserver",
                        "ovf:value": "",
                        "ovf:type": "string",
                        "ovf:userConfigurable": "false"
                    },
                    "Label": {
                        "value" : "NTP Servers"
                    },
                    "Description": {
                        "value" : "A comma-separated list of hostnames or IP addresses of NTP Servers"
                    }
                },
                {
                    "attributes": {
                        "ovf:key": "vami.hostname",
                        "ovf:value": "",
                        "ovf:type": "string",
                        "ovf:userConfigurable": "false"
                    },
                    "Label": {
                        "value" : "Hostname"
                    },
                    "Description": {
                        "value" : "The hostname for this VM. Leave blank to try to reverse lookup the IP address."
                    }
                },
                {
                    "attributes": {
                        "ovf:key": "dbpassword",
                        "ovf:value": "",
                        "ovf:type": "string",
                        "ovf:userConfigurable": "true",
                        "ovf:password": "true",
                        "ovf:qualifiers": "MinLen(8),MaxLen(32)",
                        "ovf:required": "false"
                    },
                    "Label": {
                        "ovf:msgid": "dbpassword.label",
                        "value" : "Initial database password"
                    },
                    "Description": {
                        "ovf:msgid": "dbpassword.description",
                        "value" : "This will be used as initial database password."
                    }
                },
                {
                    "attributes": {
                        "ovf:key": "enableFileIntegrity",
                        "ovf:value": "False",
                        "ovf:type": "boolean",
                        "ovf:userConfigurable": "true",
                        "ovf:required": "false"
                    },
                    "Label": {
                        "ovf:msgid": "enableFileIntegrity.label",
                        "value" : "File Integrity Flag"
                    },
                    "Description": {
                        "ovf:msgid": "enableFileIntegrity.description",
                        "value" : "This will be used as flag whether to enable file integrity."
                    }
                },
                {
                    "attributes": {
                        "ovf:key": "HCX",
                        "ovf:value": "False",
                        "ovf:type": "boolean",
                        "ovf:userConfigurable": "true",
                        "ovf:required": "false"
                    },
                    "Label": {
                        "ovf:msgid": "HCX.label",
                        "value" : "HCX Flag"
                    },
                    "Description": {
                        "ovf:msgid": "HCX.description",
                        "value" : "This will be used as flag whether to enable HCX support."
                    }
                }]
        }]
    },
    {
        "attributes": {
            "ovf:instance": "VMware_Sample_Appliance",
            "ovf:class": "network",
            "ovf:required": "false"
        },
        "Info": "Networking Properties",
        "categories": [{
            "name": "Networking Properties",
            "attributes": {
                "ovf:msgid": "network.category"
            },
            "properties": [
                {
                    "attributes": {
                        "ovf:key": "addrfamily",
                        "ovf:value": "ipv4",
                        "ovf:type": "string",
                        "ovf:userConfigurable": "true",
                        "ovf:qualifiers": "ValueMap{\"ipv4\",\"ipv6\"}",
                        "ovf:required": "true"
                    },
                    "Label": {
                        "value" : "Host Network IP Address Family"
                    },
                    "Description": {
                        "value" : "Network IP address family (i.e., 'ipv4' or 'ipv6')."
                    }
                },
                    {
                        "attributes": {
                            "ovf:key": "netmode",
                            "ovf:value": "dhcp",
                            "ovf:type": "string",
                            "ovf:userConfigurable": "true",
                            "ovf:qualifiers": "ValueMap{\"static\",\"dhcp\",\"autoconf\"}",
                            "ovf:required": "true"
                        },
                        "Label": {
                            "value" : "Host Network Mode"
                        },
                        "Description": {
                            "value" : "Network mode (i.e., 'static', 'dhcp', or 'autoconf' (IPv6 only)."
                        }
                    },
                    {
                        "attributes": {
                            "ovf:key": "gateway",
                            "ovf:value": "",
                            "ovf:type": "string",
                            "ovf:userConfigurable": "true",
                            "ovf:required": "false"
                        },
                        "Label": {
                            "ovf:msgid": "network.gateway.label",
                            "value" : "Host Network Default Gateway"
                        },
                        "Description": {
                            "ovf:msgid":"network.gateway.description",
                            "value" : "The default gateway address for this VM. (from the IP Pool associated with the vSphere network mapped to the 'Network 1' network)"
                        }
                    },
                    {
                        "attributes": {
                            "ovf:key": "domain",
                            "ovf:value": "",
                            "ovf:type": "string",
                            "ovf:userConfigurable": "true",
                            "ovf:required": "false"
                        },
                        "Label": {
                            "ovf:msgid": "network.domain.label",
                            "value" : "Domain Name"
                        },
                        "Description": {
                            "ovf:msgid": "network.domain.description",
                            "value" : "The domain name of this VM. (from the IP Pool associated with the vSphere network mapped to the 'Network 1' network)"
                        }
                    },
                    {
                        "attributes": {
                            "ovf:key": "searchpath",
                            "ovf:value": "",
                            "ovf:type": "string",
                            "ovf:userConfigurable": "false",
                            "ovf:required": "false"
                        },
                        "Label": {
                            "ovf:msgid": "network.searchpath.label",
                            "value" : "Domain Search Path"
                        },
                        "Description": {
                            "ovf:msgid": "network.searchpath.description",
                            "value" : "The domain search path (comma or space separated domain names) for this VM. (from the IP Pool associated with the vSphere network mapped to the 'Network 1' network)"
                        }
                    },
                    {
                        "attributes": {
                            "ovf:key": "DNS",
                            "ovf:value": "",
                            "ovf:type": "string",
                            "ovf:userConfigurable": "true",
                            "ovf:required": "false"
                        },
                        "Label": {
                            "ovf:msgid": "network.DNS.label",
                            "value" : "Domain Name Servers"
                        },
                        "Description": {
                            "ovf:msgid": "network.DNS.description",
                            "value": "The domain name server IP Addresses for this VM (comma separated). (from the IP Pool associated with the vSphere network mapped to the 'Network 1' network)"
                        }
                    },
                    {
                        "attributes": {
                            "ovf:key": "ip0",
                            "ovf:value": "",
                            "ovf:type": "string",
                            "ovf:userConfigurable": "true",
                            "ovf:required": "false"
                        },
                        "Label": {
                            "ovf:msgid": "network.ip0.label",
                            "value": "Network 1 IP Address"
                        },
                        "Description": {
                            "ovf:msgid": "network.ip0.description",
                            "value": "The IP address for this interface."
                        }
                    },
                    {
                        "attributes": {
                            "ovf:key": "netprefix0",
                            "ovf:value": "0",
                            "ovf:type": "int",
                            "ovf:userConfigurable": "true",
                            "ovf:required": "false"
                        },
                        "Label": {
                            "ovf:msgid": "network.netprefix0.label",
                            "value": "Network 1 Prefix"
                        },
                        "Description": {
                            "ovf:msgid": "network.netprefix0.description",
                            "value": "The network prefix for this interface."
                        }
                    }]
            }]
        },
    {
        "attributes": {
            "ovf:class": "vami",
            "ovf:instance": "VMware_Site_Recovery_Manager_Appliance",
            "ovf:required": "false"
        },
        "Info": "VAMI Properties"
    },
    {
        "attributes": {
            "ovf:class": "vm",
            "ovf:required": "false"
        },
        "Info": "VM specific properties",
        "properties": [{
            "attributes": {
                "ovf:key": "vmname",
                "ovf:value": "VMware_Site_Recovery_Manager_Appliance",
                "ovf:type": "string"
            }
        }]
    }]
}